helloworld.py
helloworld_disw-0.0.1.dist-info/LICENSE.txt
helloworld_disw-0.0.1.dist-info/METADATA
helloworld_disw-0.0.1.dist-info/WHEEL
helloworld_disw-0.0.1.dist-info/top_level.txt
helloworld_disw-0.0.1.dist-info/RECORD
