Metadata-Version: 2.1
Name: helloworld-disw
Version: 0.0.1
Summary: Say hello!
Home-page: https://github.com/lautarodc
Author: Lautaro Delgado
Author-email: ldc0295@gmail.com
License: UNKNOWN
Platform: UNKNOWN
Classifier: Programming Language :: Python :: 3
Classifier: License :: OSI Approved :: MIT License
Classifier: Operating System :: OS Independent
Requires-Dist: blessings (~=1.7)
Provides-Extra: dev
Requires-Dist: pytest (>=3.7) ; extra == 'dev'
Requires-Dist: check-manifest ; extra == 'dev'
Requires-Dist: twine ; extra == 'dev'
